semilattices/__init__.py
semilattices/_coordinatesemilatticebase.py
semilattices/_datastructures.py
semilattices/_decreasingcoordinatesemilatticebase.py
semilattices/_exceptions.py
semilattices/_iterables.py
semilattices/_misc.py
semilattices/_objectbase.py
semilattices/_semilatticebase.py
semilattices/_sortedcoordinatesemilatticebase.py
semilattices/_sorteddecreasingcoordinatesemilatticebase.py
semilattices/_utilities.py
semilattices/_version.py
semilattices/_vertices.py
semilattices/tests/__init__.py
semilattices/tests/semilattices_test.py
semilattices-1.0.1.dist-info/METADATA
semilattices-1.0.1.dist-info/WHEEL
semilattices-1.0.1.dist-info/top_level.txt
semilattices-1.0.1.dist-info/zip-safe
semilattices-1.0.1.dist-info/RECORD
